phbuilder/__init__.py
phbuilder/mdp.py
phbuilder/parsecmdline.py
phbuilder/phbuilder.py
phbuilder/sanitize.py
phbuilder/structure.py
phbuilder/user.py
phbuilder/ffield/README.md
phbuilder/ffield/lambdagrouptypes.dat
phbuilder/ffield/residuetypes.dat
phbuilder/ffield/charmm36-mar2019-cphmd.ff/atomtypes.atp
phbuilder/ffield/charmm36-mar2019-cphmd.ff/cmap.itp
phbuilder/ffield/charmm36-mar2019-cphmd.ff/ffbonded.itp
phbuilder/ffield/charmm36-mar2019-cphmd.ff/ffnonbonded.itp
phbuilder/ffield/charmm36-mar2019-cphmd.ff/forcefield.doc
phbuilder/ffield/charmm36-mar2019-cphmd.ff/forcefield.itp
phbuilder/ffield/charmm36-mar2019-cphmd.ff/gb.itp
phbuilder/ffield/charmm36-mar2019-cphmd.ff/ions.itp
phbuilder/ffield/charmm36-mar2019-cphmd.ff/merged.arn
phbuilder/ffield/charmm36-mar2019-cphmd.ff/merged.c.tdb
phbuilder/ffield/charmm36-mar2019-cphmd.ff/merged.hdb
phbuilder/ffield/charmm36-mar2019-cphmd.ff/merged.n.tdb
phbuilder/ffield/charmm36-mar2019-cphmd.ff/merged.r2b
phbuilder/ffield/charmm36-mar2019-cphmd.ff/merged.rtp
phbuilder/ffield/charmm36-mar2019-cphmd.ff/merged.vsd
phbuilder/ffield/charmm36-mar2019-cphmd.ff/nbfix.itp
phbuilder/ffield/charmm36-mar2019-cphmd.ff/old_c36_cmap.itp
phbuilder/ffield/charmm36-mar2019-cphmd.ff/popc.itp
phbuilder/ffield/charmm36-mar2019-cphmd.ff/spc.itp
phbuilder/ffield/charmm36-mar2019-cphmd.ff/spce.itp
phbuilder/ffield/charmm36-mar2019-cphmd.ff/tip3p.itp
phbuilder/ffield/charmm36-mar2019-cphmd.ff/tip4p.itp
phbuilder/ffield/charmm36-mar2019-cphmd.ff/watermodels.dat
tests/__init__.py
tests/test_genparams.py
tests/test_gentopol.py
tests/test_neutralize.py
tests/testutils.py
phbuilder-1.3.dist-info/LICENSE
phbuilder-1.3.dist-info/METADATA
phbuilder-1.3.dist-info/WHEEL
phbuilder-1.3.dist-info/entry_points.txt
phbuilder-1.3.dist-info/top_level.txt
phbuilder-1.3.dist-info/RECORD
