Metadata-Version: 2.1
Name: phbuilder
Version: 1.3
Summary: System builder for constant-pH simulations in GROMACS.
Home-page: https://gitlab.com/gromacs-constantph/phbuilder
Author: Anton Jansen
Author-email: anton.jansen@scilifelab.se
Project-URL: Bug Tracker, https://gitlab.com/gromacs-constantph/phbuilder/-/issues
Classifier: Programming Language :: Python :: 3
Classifier: License :: OSI Approved :: GNU General Public License v3 (GPLv3)
Classifier: Development Status :: 5 - Production/Stable
Classifier: Topic :: Scientific/Engineering :: Physics
Classifier: Topic :: Scientific/Engineering :: Chemistry
Classifier: Intended Audience :: Science/Research
Classifier: Natural Language :: English
Requires-Python: >=3.8
License-File: LICENSE
Requires-Dist: argcomplete>=3.1.1
Requires-Dist: configparser>=6.0.0
Requires-Dist: sympy>=1.12
Requires-Dist: numpy
